iamauth/__init__.py
iamauth/__main__.py
iamauth/sigv4.py
iamauth/sigv4a.py
requests_iamauth-1.0.0.dist-info/entry_points.txt
requests_iamauth-1.0.0.dist-info/licenses/LICENSE
requests_iamauth-1.0.0.dist-info/WHEEL
requests_iamauth-1.0.0.dist-info/METADATA
requests_iamauth-1.0.0.dist-info/RECORD
