Metadata-Version: 2.4
Name: requests-iamauth
Version: 1.0.0
Summary: AWS IAM Authorizer.
Author-email: Alexander Mancevice <alexander.mancevice@hey.com>
Requires-Python: >= 3.8
Classifier: Development Status :: 5 - Production/Stable
Classifier: Environment :: Console
Classifier: Intended Audience :: Developers
Classifier: License :: OSI Approved :: MIT License
Classifier: Operating System :: OS Independent
Classifier: Programming Language :: Python :: 3
Classifier: Programming Language :: Python :: 3.8
Classifier: Programming Language :: Python :: 3.9
Classifier: Programming Language :: Python :: 3.10
Classifier: Programming Language :: Python :: 3.11
Classifier: Programming Language :: Python :: 3.12
Classifier: Programming Language :: Python :: 3.13
Classifier: Topic :: Utilities
License-File: LICENSE
Requires-Dist: awscrt
Requires-Dist: boto3
Requires-Dist: requests
Project-URL: Home, https://github.com/amancevice/requests-iamauth
